{
  "$schema": "http://cyclonedx.org/schema/bom-1.4.schema.json",
  "bomFormat": "CycloneDX",
  "specVersion": "1.4",
  "serialNumber": "urn:uuid:3f0850fd-28c1-4972-9eb0-0525357c60e2",
  "version": 1,
  "metadata": {
    "timestamp": "2022-10-07T17:19:47.551700+00:00",
    "tools": [
      {
        "vendor": "CycloneDX",
        "name": "cyclonedx-bom",
        "version": "3.6.3"
      },
      {
        "vendor": "CycloneDX",
        "name": "cyclonedx-python-lib",
        "version": "2.7.1",
        "externalReferences": [
          {
            "url": "https://github.com/CycloneDX/cyclonedx-python-lib/actions",
            "type": "build-system"
          },
          {
            "url": "https://pypi.org/project/cyclonedx-python-lib/",
            "type": "distribution"
          },
          {
            "url": "https://cyclonedx.github.io/cyclonedx-python-lib/",
            "type": "documentation"
          },
          {
            "url": "https://github.com/CycloneDX/cyclonedx-python-lib/issues",
            "type": "issue-tracker"
          },
          {
            "url": "https://github.com/CycloneDX/cyclonedx-python-lib/blob/main/LICENSE",
            "type": "license"
          },
          {
            "url": "https://github.com/CycloneDX/cyclonedx-python-lib/blob/main/CHANGELOG.md",
            "type": "release-notes"
          },
          {
            "url": "https://github.com/CycloneDX/cyclonedx-python-lib",
            "type": "vcs"
          },
          {
            "url": "https://cyclonedx.org",
            "type": "website"
          }
        ]
      }
    ]
  },
  "components": [
    {
      "type": "library",
      "bom-ref": "fce238e8-6845-47bd-b7bf-372f65e67051",
      "name": "PyYAML",
      "version": "6.0",
      "purl": "pkg:pypi/pyyaml@6.0"
    },
    {
      "type": "library",
      "bom-ref": "798904bb-6a00-436c-87c0-7dc286c7e55d",
      "name": "typer",
      "version": "0.6.1",
      "purl": "pkg:pypi/typer@0.6.1"
    }
  ],
  "dependencies": [
    {
      "ref": "fce238e8-6845-47bd-b7bf-372f65e67051",
      "dependsOn": []
    },
    {
      "ref": "798904bb-6a00-436c-87c0-7dc286c7e55d",
      "dependsOn": []
    }
  ]
}
